codatio/__init__.py
codatio/account_transactions.py
codatio/accounts.py
codatio/bank_account_transactions.py
codatio/bank_accounts.py
codatio/bill_credit_notes.py
codatio/bill_payments.py
codatio/bills.py
codatio/credit_notes.py
codatio/customers.py
codatio/direct_costs.py
codatio/direct_incomes.py
codatio/financials.py
codatio/info.py
codatio/invoices.py
codatio/items.py
codatio/journal_entries.py
codatio/journals.py
codatio/payment_methods.py
codatio/payments.py
codatio/purchase_orders.py
codatio/reports.py
codatio/sales_orders.py
codatio/sdk.py
codatio/suppliers.py
codatio/tax_rates.py
codatio/tracking_categories.py
codatio/transfers.py
codatio/models/__init__.py
codatio/models/operations/__init__.py
codatio/models/operations/donwload_invoice_attachment.py
codatio/models/operations/download_bill_attachment.py
codatio/models/operations/download_customer_attachment.py
codatio/models/operations/download_direct_cost_attachment.py
codatio/models/operations/download_direct_income_attachment.py
codatio/models/operations/download_supplier_attachment.py
codatio/models/operations/get_account.py
codatio/models/operations/get_account_transaction.py
codatio/models/operations/get_accounts.py
codatio/models/operations/get_aged_creditors_report.py
codatio/models/operations/get_aged_debtors_report.py
codatio/models/operations/get_all_bank_account.py
codatio/models/operations/get_balance_sheet.py
codatio/models/operations/get_bank_account.py
codatio/models/operations/get_bank_account_push_options.py
codatio/models/operations/get_bill.py
codatio/models/operations/get_bill_attachment.py
codatio/models/operations/get_bill_attachments.py
codatio/models/operations/get_bill_credit_note.py
codatio/models/operations/get_bill_payments.py
codatio/models/operations/get_cash_flow_statement.py
codatio/models/operations/get_company_info.py
codatio/models/operations/get_credit_note.py
codatio/models/operations/get_customer.py
codatio/models/operations/get_customer_attachment.py
codatio_accounting-0.1.1.dist-info/METADATA
codatio_accounting-0.1.1.dist-info/WHEEL
codatio_accounting-0.1.1.dist-info/top_level.txt
codatio_accounting-0.1.1.dist-info/RECORD
